do_mpc/__init__.py
do_mpc/_version.py
do_mpc/data.py
do_mpc/graphics.py
do_mpc/optimizer.py
do_mpc/simulator.py
do_mpc/approximateMPC/__init__.py
do_mpc/approximateMPC/_ampc.py
do_mpc/approximateMPC/_ampc_sampler.py
do_mpc/approximateMPC/_ampcsettings.py
do_mpc/approximateMPC/_trainer.py
do_mpc/controller/__init__.py
do_mpc/controller/_controllersettings.py
do_mpc/controller/_lqr.py
do_mpc/controller/_mpc.py
do_mpc/differentiator/__init__.py
do_mpc/differentiator/_nlpdifferentiator.py
do_mpc/differentiator/helper.py
do_mpc/estimator/__init__.py
do_mpc/estimator/_base.py
do_mpc/estimator/_ekf.py
do_mpc/estimator/_estimatorsettings.py
do_mpc/estimator/_mhe.py
do_mpc/model/__init__.py
do_mpc/model/_dae2odeconversion.py
do_mpc/model/_iteratedvariables.py
do_mpc/model/_linearize.py
do_mpc/model/_linearmodel.py
do_mpc/model/_model.py
do_mpc/opcua/__init__.py
do_mpc/opcua/_base.py
do_mpc/opcua/_client.py
do_mpc/opcua/_helper.py
do_mpc/opcua/_server.py
do_mpc/sampling/__init__.py
do_mpc/sampling/_datahandler.py
do_mpc/sampling/_sampler.py
do_mpc/sampling/_samplingplanner.py
do_mpc/sysid/__init__.py
do_mpc/sysid/_onnxconversion.py
do_mpc/tools/__init__.py
do_mpc/tools/_casstructure.py
do_mpc/tools/_indexedproperty.py
do_mpc/tools/_structure.py
do_mpc/tools/_timer.py
do_mpc-5.0.1.dist-info/licenses/LICENSE.txt
do_mpc-5.0.1.dist-info/METADATA
do_mpc-5.0.1.dist-info/WHEEL
do_mpc-5.0.1.dist-info/top_level.txt
do_mpc-5.0.1.dist-info/RECORD
