Metadata-Version: 2.4
Name: do_mpc
Version: 5.0.1
Home-page: https://www.do-mpc.com
Author: Sergio Lucia and Felix Fiedler
Author-email: sergio.lucia@tu-berlin.de
License: GNU Lesser General Public License version 3
License-File: LICENSE.txt
Requires-Dist: casadi>=3.6.0
Requires-Dist: scipy
Requires-Dist: numpy
Requires-Dist: matplotlib
Requires-Dist: pandas
Requires-Dist: torch>2.0.0
Provides-Extra: full
Requires-Dist: onnx>=1.13.0; extra == "full"
Requires-Dist: ipykernel; extra == "full"
Requires-Dist: packaging; extra == "full"
Requires-Dist: asyncua; extra == "full"
Dynamic: author
Dynamic: author-email
Dynamic: description
Dynamic: description-content-type
Dynamic: home-page
Dynamic: license
Dynamic: license-file
Dynamic: provides-extra
Dynamic: requires-dist
